authsignals/__init__.py
django_authsignals-0.1.0.dist-info/LICENSE
django_authsignals-0.1.0.dist-info/METADATA
django_authsignals-0.1.0.dist-info/WHEEL
django_authsignals-0.1.0.dist-info/top_level.txt
django_authsignals-0.1.0.dist-info/RECORD
